gravity/__init__.py
gravity/cli.py
gravity/config_manager.py
gravity/io.py
gravity/options.py
gravity/settings.py
gravity/state.py
gravity/commands/__init__.py
gravity/commands/cmd_exec.py
gravity/commands/cmd_follow.py
gravity/commands/cmd_graceful.py
gravity/commands/cmd_list.py
gravity/commands/cmd_pm.py
gravity/commands/cmd_restart.py
gravity/commands/cmd_show.py
gravity/commands/cmd_shutdown.py
gravity/commands/cmd_start.py
gravity/commands/cmd_status.py
gravity/commands/cmd_stop.py
gravity/commands/cmd_update.py
gravity/process_manager/__init__.py
gravity/process_manager/multiprocessing.py
gravity/process_manager/supervisor.py
gravity/process_manager/systemd.py
gravity/util/__init__.py
gravity-1.2.0.dist-info/licenses/LICENSE
gravity-1.2.0.dist-info/METADATA
gravity-1.2.0.dist-info/WHEEL
gravity-1.2.0.dist-info/entry_points.txt
gravity-1.2.0.dist-info/top_level.txt
gravity-1.2.0.dist-info/RECORD
