Metadata-Version: 2.4
Name: gravity
Version: 1.2.0
Summary: Command-line utilities to assist in managing Galaxy servers
Home-page: https://github.com/galaxyproject/gravity
Author: The Galaxy Team
Author-email: team@galaxyproject.org
License: MIT
Keywords: gravity galaxy
Classifier: Intended Audience :: System Administrators
Classifier: License :: OSI Approved :: MIT License
Classifier: Natural Language :: English
Classifier: Operating System :: POSIX
Classifier: Programming Language :: Python :: 3
Classifier: Programming Language :: Python :: 3.8
Classifier: Programming Language :: Python :: 3.9
Classifier: Programming Language :: Python :: 3.10
Classifier: Programming Language :: Python :: 3.11
Classifier: Programming Language :: Python :: 3.12
Classifier: Programming Language :: Python :: 3.13
Classifier: Programming Language :: Python :: 3.14
Requires-Python: >=3.8
License-File: LICENSE
Requires-Dist: Click
Requires-Dist: supervisor
Requires-Dist: pyyaml
Requires-Dist: packaging
Requires-Dist: pydantic<3,>=2
Requires-Dist: pydantic-settings
Requires-Dist: jsonref
Requires-Dist: requests
Requires-Dist: requests-unixsocket
Dynamic: author
Dynamic: author-email
Dynamic: classifier
Dynamic: description
Dynamic: description-content-type
Dynamic: home-page
Dynamic: keywords
Dynamic: license
Dynamic: license-file
Dynamic: requires-dist
Dynamic: requires-python
Dynamic: summary
